eia/__init__.py
eia/loaders/__init__.py
eia/loaders/load_dataframe.py
eia/scraping/__init__.py
eia/scraping/api.py
eia/scraping/api_key.py
eia/scraping/download_data.py
eia/scraping/eia_client.py
eia/utils/__init__.py
eia/utils/path.py
eia_py_api-0.0.1.dist-info/METADATA
eia_py_api-0.0.1.dist-info/WHEEL
eia_py_api-0.0.1.dist-info/top_level.txt
eia_py_api-0.0.1.dist-info/RECORD
